skillport_mcp/__init__.py
skillport_mcp-1.1.0.dist-info/METADATA
skillport_mcp-1.1.0.dist-info/WHEEL
skillport_mcp-1.1.0.dist-info/entry_points.txt
skillport_mcp-1.1.0.dist-info/RECORD
