Metadata-Version: 2.4
Name: skillport-mcp
Version: 1.1.0
Summary: SkillPort MCP server (indexed search + tools). See https://github.com/gotalab/skillport for documentation.
Project-URL: Homepage, https://github.com/gotalab/skillport
Project-URL: Repository, https://github.com/gotalab/skillport
Author: Gota
License-Expression: MIT
Keywords: agent-skills,context-engineering,mcp,mcp-server
Classifier: Development Status :: 4 - Beta
Classifier: License :: OSI Approved :: MIT License
Classifier: Programming Language :: Python :: 3
Classifier: Programming Language :: Python :: 3 :: Only
Classifier: Programming Language :: Python :: 3.10
Classifier: Programming Language :: Python :: 3.11
Classifier: Programming Language :: Python :: 3.12
Classifier: Programming Language :: Python :: 3.13
Classifier: Programming Language :: Python :: 3.14
Requires-Python: >=3.10
Requires-Dist: fastmcp>=2.0.0
Requires-Dist: lancedb>=0.26.0
Requires-Dist: openai>=1.0.0
Requires-Dist: pylance
Requires-Dist: skillport-core==1.1.0
Requires-Dist: tantivy>=0.19.0
